{
  "Twist of Fate/Twist of Fate_Episode_1": [
    "mazen",
    "Edmond"
  ],
  "Twist of Fate/Twist of Fate_Episode_2": [
    "mazen"
  ],
  "Twist of Fate/Twist of Fate_Episode_3": [
    "mazen"
  ],
  "Twist of Fate/Twist of Fate_Episode_5": [
    "mazen",
    "Jad"
  ],
  "Twist of Fate/Twist of Fate_Episode_4": [
    "mazen"
  ],
  "Twist of Fate/Twist of Fate_Episode_6": [
    "mazen",
    "Jad"
  ],
  "Twist of Fate/Twist of Fate_Episode_7": [
    "mazen"
  ],
  "Twist of Fate/Twist of Fate_Episode_8": [
    "mazen"
  ],
  "Twist of Fate/Twist of Fate_Episode_9": [
    "Jad"
  ],
  "Twist of Fate/Twist of Fate_Episode_10": [
    "IPH",
    "Maram"
  ]
}